pdme/__init__.py
pdme/calculations/__init__.py
pdme/inputs/__init__.py
pdme/inputs/dot_inputs.py
pdme/measurement/__init__.py
pdme/measurement/dot_measure.py
pdme/measurement/dot_pair_measure.py
pdme/measurement/input_types.py
pdme/measurement/oscillating_dipole.py
pdme/meta.py
pdme/model/__init__.py
pdme/model/fixed_magnitude_model.py
pdme/model/log_spaced_random_choice_fixed_orientation_model.py
pdme/model/log_spaced_random_choice_model.py
pdme/model/log_spaced_random_choice_xy_model.py
pdme/model/model.py
pdme/model/multidipole_fixed_magnitude_model.py
pdme/model/random_count_multidipole_fixed_magnitude_model.py
pdme/py.typed
pdme/subspace_simulation/__init__.py
pdme/subspace_simulation/mcmc_costs.py
pdme/util/__init__.py
pdme/util/fast_nonlocal_spectrum.py
pdme/util/fast_v_calc.py
pdme-1.5.0.dist-info/METADATA
pdme-1.5.0.dist-info/WHEEL
pdme-1.5.0.dist-info/RECORD
